leetcodelib/__init__.py
leetcodelib/utils/__init__.py
leetcodelib/utils/link_helper.py
leetcodelib/utils/load_typing.py
leetcodelib/utils/tree_helper.py
leetcodelib-0.1.0.dist-info/METADATA
leetcodelib-0.1.0.dist-info/WHEEL
leetcodelib-0.1.0.dist-info/top_level.txt
leetcodelib-0.1.0.dist-info/RECORD
